[
    [
        {
            "BetTableId": "DK_e52c9399_f5328492_NBA",
            "Odds Table": {
                "Book Name": "DK",
                "Away Spread": "+7.5",
                "Away Spread Odds": "−115",
                "Away ML": "+235",
                "Home Spread": "-7.5",
                "Home Spread Odds": "−105",
                "Home ML": "−290",
                "Total": "218.5",
                "Over Total Odds": "−112",
                "Under Total Odds": "−108"
            },
            "MatchupID": "e52c9399_f5328492_NBA",
            "Info Table": {
                "Away Team": "PHO Suns",
                "Away Team Rank Name": "Phoenix",
                "Away Abv": "PHX",
                "Away ID": "e52c9399",
                "Home Team": "MIN Timberwolves",
                "Home Team Rank Name": "Minnesota",
                "Home Abv": "MIN",
                "Home ID": "f5328492",
                "Start Time": "3:40PM",
                "League": "NBA"
            }
        }
    ],
    [
        {
            "BetTableId": "DK_8d47be6d_dc435e0a_NBA",
            "Odds Table": {
                "Book Name": "DK",
                "Away Spread": "+3.5",
                "Away Spread Odds": "−108",
                "Away ML": "+142",
                "Home Spread": "-3.5",
                "Home Spread Odds": "−112",
                "Home ML": "−170",
                "Total": "228",
                "Over Total Odds": "−112",
                "Under Total Odds": "−108"
            },
            "MatchupID": "8d47be6d_dc435e0a_NBA",
            "Info Table": {
                "Away Team": "MIA Heat",
                "Away Team Rank Name": "Miami",
                "Away Abv": "MIA",
                "Away ID": "8d47be6d",
                "Home Team": "IND Pacers",
                "Home Team Rank Name": "Indiana",
                "Home Abv": "IND",
                "Home ID": "dc435e0a",
                "Start Time": "5:10PM",
                "League": "NBA"
            }
        }
    ],
    [
        {
            "BetTableId": "DK_73c7ef49_5a31e1ff_NBA",
            "Odds Table": {
                "Book Name": "DK",
                "Away Spread": "+11.5",
                "Away Spread Odds": "−110",
                "Away ML": "+455",
                "Home Spread": "-11.5",
                "Home Spread Odds": "−110",
                "Home ML": "−625",
                "Total": "222.5",
                "Over Total Odds": "−112",
                "Under Total Odds": "−108"
            },
            "MatchupID": "73c7ef49_5a31e1ff_NBA",
            "Info Table": {
                "Away Team": "CHA Hornets",
                "Away Team Rank Name": "Charlotte",
                "Away Abv": "CHA",
                "Away ID": "73c7ef49",
                "Home Team": "CLE Cavaliers",
                "Home Team Rank Name": "Cleveland",
                "Home Abv": "CLE",
                "Home ID": "5a31e1ff",
                "Start Time": "6:10PM",
                "League": "NBA"
            }
        }
    ],
    [
        {
            "BetTableId": "DK_59dd0ac4_d1e32cbe_NBA",
            "Odds Table": {
                "Book Name": "DK",
                "Away Spread": "+5",
                "Away Spread Odds": "−108",
                "Away ML": "+170",
                "Home Spread": "-5",
                "Home Spread Odds": "−112",
                "Home ML": "−205",
                "Total": "228.5",
                "Over Total Odds": "−105",
                "Under Total Odds": "−115"
            },
            "MatchupID": "59dd0ac4_d1e32cbe_NBA",
            "Info Table": {
                "Away Team": "DEN Nuggets",
                "Away Team Rank Name": "Denver",
                "Away Abv": "DEN",
                "Away ID": "59dd0ac4",
                "Home Team": "MEM Grizzlies",
                "Home Team Rank Name": "Memphis",
                "Home Abv": "MEM",
                "Home ID": "d1e32cbe",
                "Start Time": "6:10PM",
                "League": "NBA"
            }
        }
    ],
    [
        {
            "BetTableId": "DK_18a9d733_dd4357ee_NBA",
            "Odds Table": {
                "Book Name": "DK",
                "Away Spread": "-5.5",
                "Away Spread Odds": "−110",
                "Away ML": "−218",
                "Home Spread": "+5.5",
                "Home Spread Odds": "−110",
                "Home ML": "+180",
                "Total": "230.5",
                "Over Total Odds": "−112",
                "Under Total Odds": "−108"
            },
            "MatchupID": "18a9d733_dd4357ee_NBA",
            "Info Table": {
                "Away Team": "DET Pistons",
                "Away Team Rank Name": "Detroit",
                "Away Abv": "DET",
                "Away ID": "18a9d733",
                "Home Team": "WAS Wizards",
                "Home Team Rank Name": "Washington",
                "Home Abv": "WAS",
                "Home ID": "dd4357ee",
                "Start Time": "6:10PM",
                "League": "NBA"
            }
        }
    ],
    [
        {
            "BetTableId": "DK_354ef58_8e06f0a2_NBA",
            "Odds Table": {
                "Book Name": "DK",
                "Away Spread": "-3.5",
                "Away Spread Odds": "−112",
                "Away ML": "−170",
                "Home Spread": "+3.5",
                "Home Spread Odds": "−108",
                "Home ML": "+142",
                "Total": "229",
                "Over Total Odds": "−105",
                "Under Total Odds": "−115"
            },
            "MatchupID": "354ef58_8e06f0a2_NBA",
            "Info Table": {
                "Away Team": "ATL Hawks",
                "Away Team Rank Name": "Atlanta",
                "Away Abv": "ATL",
                "Away ID": "354ef58",
                "Home Team": "POR Trail Blazers",
                "Home Team Rank Name": "Portland",
                "Home Abv": "POR",
                "Home ID": "8e06f0a2",
                "Start Time": "6:10PM",
                "League": "NBA"
            }
        }
    ],
    [
        {
            "BetTableId": "DK_6eb04a4e_65ba1118_NBA",
            "Odds Table": {
                "Book Name": "DK",
                "Away Spread": "+9.5",
                "Away Spread Odds": "−110",
                "Away ML": "+340",
                "Home Spread": "-9.5",
                "Home Spread Odds": "−110",
                "Home ML": "−440",
                "Total": "219.5",
                "Over Total Odds": "−112",
                "Under Total Odds": "−108"
            },
            "MatchupID": "6eb04a4e_65ba1118_NBA",
            "Info Table": {
                "Away Team": "BKN Nets",
                "Away Team Rank Name": "Brooklyn",
                "Away Abv": "BKN",
                "Away ID": "6eb04a4e",
                "Home Team": "NY Knicks",
                "Home Team Rank Name": "New York",
                "Home Abv": "NYK",
                "Home ID": "65ba1118",
                "Start Time": "7:10PM",
                "League": "NBA"
            }
        }
    ],
    [
        {
            "BetTableId": "DK_48eb7bb_88f1c3e9_NBA",
            "Odds Table": {
                "Book Name": "DK",
                "Away Spread": "+8",
                "Away Spread Odds": "−115",
                "Away ML": "+245",
                "Home Spread": "-8",
                "Home Spread Odds": "−105",
                "Home ML": "−305",
                "Total": "229",
                "Over Total Odds": "−108",
                "Under Total Odds": "−112"
            },
            "MatchupID": "48eb7bb_88f1c3e9_NBA",
            "Info Table": {
                "Away Team": "DAL Mavericks",
                "Away Team Rank Name": "Dallas",
                "Away Abv": "DAL",
                "Away ID": "48eb7bb",
                "Home Team": "OKC Thunder",
                "Home Team Rank Name": "Okla City",
                "Home Abv": "OKC",
                "Home ID": "88f1c3e9",
                "Start Time": "7:10PM",
                "League": "NBA"
            }
        }
    ],
    [
        {
            "BetTableId": "DK_4005c299_f3d50c2_NBA",
            "Odds Table": {
                "Book Name": "DK",
                "Away Spread": "-4.5",
                "Away Spread Odds": "−112",
                "Away ML": "−185",
                "Home Spread": "+4.5",
                "Home Spread Odds": "−108",
                "Home ML": "+154",
                "Total": "234",
                "Over Total Odds": "−112",
                "Under Total Odds": "−108"
            },
            "MatchupID": "4005c299_f3d50c2_NBA",
            "Info Table": {
                "Away Team": "HOU Rockets",
                "Away Team Rank Name": "Houston",
                "Away Abv": "HOU",
                "Away ID": "4005c299",
                "Home Team": "CHI Bulls",
                "Home Team Rank Name": "Chicago",
                "Home Abv": "CHI",
                "Home ID": "f3d50c2",
                "Start Time": "7:10PM",
                "League": "NBA"
            }
        }
    ],
    [
        {
            "BetTableId": "DK_b1e0538c_88571b9e_NBA",
            "Odds Table": {
                "Book Name": "DK",
                "Away Spread": "+9.5",
                "Away Spread Odds": "−105",
                "Away ML": "+360",
                "Home Spread": "-9.5",
                "Home Spread Odds": "−115",
                "Home ML": "−470",
                "Total": "221.5",
                "Over Total Odds": "−112",
                "Under Total Odds": "−108"
            },
            "MatchupID": "b1e0538c_88571b9e_NBA",
            "Info Table": {
                "Away Team": "UTA Jazz",
                "Away Team Rank Name": "Utah",
                "Away Abv": "UTA",
                "Away ID": "b1e0538c",
                "Home Team": "LA Clippers",
                "Home Team Rank Name": "LA Clippers",
                "Home Abv": "LAC",
                "Home ID": "88571b9e",
                "Start Time": "9:10PM",
                "League": "NBA"
            }
        }
    ]
]